rehoused_nlp
tests
