Metadata-Version: 2.1
Name: rehoused-nlp
Version: 0.0.0.2
Summary: medspaCy NLP pipeline for detecting patient housing stability.
Home-page: UNKNOWN
Author: alec.chapman
Author-email: alec.chapman@hsc.utah.edu
License: UNKNOWN
Platform: UNKNOWN
